exobrain/__init__.py
exobrain/config.example.yaml
exobrain/config.py
exobrain/agent/__init__.py
exobrain/agent/base.py
exobrain/agent/events.py
exobrain/cli/__init__.py
exobrain/cli/chat_commands.py
exobrain/cli/chat_permissions.py
exobrain/cli/chat_ui.py
exobrain/cli/config_commands.py
exobrain/cli/config_wizard.py
exobrain/cli/constitution_commands.py
exobrain/cli/init_commands.py
exobrain/cli/mcp_commands.py
exobrain/cli/models_commands.py
exobrain/cli/sessions_commands.py
exobrain/cli/skills_commands.py
exobrain/cli/task_commands.py
exobrain/cli/util.py
exobrain/cli/tui/chat/__init__.py
exobrain/cli/tui/chat/app.py
exobrain/cli/tui/chat/widgets/__init__.py
exobrain/cli/tui/chat/widgets/chat_history.py
exobrain/cli/tui/chat/widgets/header.py
exobrain/cli/tui/chat/widgets/input_area.py
exobrain/cli/tui/chat/widgets/message.py
exobrain/cli/tui/chat/widgets/status_bar.py
exobrain/cli/tui/chat/widgets/tool_sidebar.py
exobrain/cli/tui/skills/__init__.py
exobrain/cli/tui/skills/app.py
exobrain/cli/tui/skills/widgets/__init__.py
exobrain/cli/tui/skills/widgets/skill_detail.py
exobrain/cli/tui/skills/widgets/skills_list.py
exobrain/constitutions/builtin-coding.md
exobrain/constitutions/builtin-default.md
exobrain/mcp/__init__.py
exobrain/mcp/base.py
exobrain/mcp/context7_client.py
exobrain/memory/__init__.py
exobrain/memory/conversations.py
exobrain/memory/loader.py
exobrain/memory/storage.py
exobrain/memory/handlers/__init__.py
exobrain/memory/handlers/base.py
exobrain/memory/handlers/factory.py
exobrain/memory/handlers/truncating.py
exobrain/providers/__init__.py
exobrain/providers/base.py
exobrain/providers/factory.py
exobrain/providers/gemini_provider.py
exobrain/providers/openai_compatible_provider.py
exobrain/providers/openai_provider.py
exobrain/skills/__init__.py
exobrain/skills/loader.py
exobrain/skills/manager.py
exobrain/skills/anthropic/README.md
exobrain/skills/anthropic/THIRD_PARTY_NOTICES.md
exobrain/skills/anthropic/skills/algorithmic-art/SKILL.md
exobrain-0.2.1.dist-info/licenses/LICENSE
exobrain-0.2.1.dist-info/METADATA
exobrain-0.2.1.dist-info/WHEEL
exobrain-0.2.1.dist-info/entry_points.txt
exobrain-0.2.1.dist-info/top_level.txt
exobrain-0.2.1.dist-info/RECORD
