Metadata-Version: 2.4
Name: exobrain
Version: 0.2.1
Summary: A toy AI assistant with agent capabilities and file system access
Author-email: VisualDust <gavin@gong.host>
License: MIT
Project-URL: Homepage, https://github.com/visualDust/exobrain
Project-URL: Repository, https://github.com/visualDust/exobrain
Keywords: ai,assistant,agent,cli
Classifier: Development Status :: 3 - Alpha
Classifier: Intended Audience :: Developers
Classifier: Intended Audience :: End Users/Desktop
Classifier: Programming Language :: Python :: 3.10
Classifier: Programming Language :: Python :: 3.11
Classifier: Programming Language :: Python :: 3.12
Classifier: Topic :: Scientific/Engineering :: Artificial Intelligence
Requires-Python: <4,>=3.10
License-File: LICENSE
Requires-Dist: pydantic<3,>=2.5.0
Requires-Dist: pydantic-settings<3,>=2.1.0
Requires-Dist: rich<14,>=13.7.0
Requires-Dist: click<9,>=8.1.7
Requires-Dist: aiofiles<24,>=23.2.1
Requires-Dist: httpx<0.27,>=0.26.0
Requires-Dist: pyyaml<7,>=6.0.1
Requires-Dist: python-dotenv<2,>=1.0.0
Requires-Dist: beautifulsoup4<5,>=4.12.0
Requires-Dist: lxml<6,>=5.0.0
Requires-Dist: pre-commit>=3.8.0
Requires-Dist: textual>=0.89.0
Requires-Dist: ddgs>=9.5.2
Requires-Dist: pypdf<5,>=4.0.0
Provides-Extra: openai
Requires-Dist: openai<2,>=1.7.0; extra == "openai"
Provides-Extra: anthropic
Requires-Dist: anthropic<0.9,>=0.8.0; extra == "anthropic"
Provides-Extra: all
Requires-Dist: openai<2,>=1.7.0; extra == "all"
Requires-Dist: anthropic<0.9,>=0.8.0; extra == "all"
Dynamic: license-file
